alertlogic/__init__.py
alertlogic/__init__.pyc
alertlogic/auth.py
alertlogic/auth.pyc
alertlogic/region.py
alertlogic/region.pyc
alertlogic/service.py
alertlogic/service.pyc
alertlogic/services.py
alertlogic/services.pyc
alertlogic/tests/__init__.py
alertlogic/tests/__init__.pyc
alertlogic/tests/assets_query_tests.py
alertlogic/tests/credentials_tests.py
alertlogic/tests/deployments_tests.py
alertlogic/tests/launcher_tests.py
alertlogic/tests/mock.py
alertlogic/tests/mock.pyc
alertlogic/tests/otis_tests.py
alertlogic/tests/saturn_tests.py
alertlogic/tests/scan_collect_tests.py
alertlogic/tests/scheduler_tests.py
alertlogic/tests/skaletor_tests.py
alertlogic/tests/sources_tests.py
alertlogic/tests/themis_tests.py
alertlogic/tests/__pycache__/assets_query_tests.cpython-27-PYTEST.pyc
alertlogic/tests/__pycache__/credentials_tests.cpython-27-PYTEST.pyc
alertlogic/tests/__pycache__/deployments_tests.cpython-27-PYTEST.pyc
alertlogic/tests/__pycache__/launcher_tests.cpython-27-PYTEST.pyc
alertlogic/tests/__pycache__/otis_tests.cpython-27-PYTEST.pyc
alertlogic/tests/__pycache__/saturn_tests.cpython-27-PYTEST.pyc
alertlogic/tests/__pycache__/scan_collect_tests.cpython-27-PYTEST.pyc
alertlogic/tests/__pycache__/scheduler_tests.cpython-27-PYTEST.pyc
alertlogic/tests/__pycache__/skaletor_tests.cpython-27-PYTEST.pyc
alertlogic/tests/__pycache__/sources_tests.cpython-27-PYTEST.pyc
alertlogic/tests/__pycache__/themis_tests.cpython-27-PYTEST.pyc
alertlogiccli/__init__.py
alertlogiccli/alertlogic_console.py
alertlogiccli/command.py
alertlogiccli/config.py
alertlogiccli/cons.py
alertlogiccli/context.py
alertlogiccli/credentials.py
alertlogiccli/commands/__init__.py
alertlogiccli/commands/deployment/__init__.py
alertlogiccli/commands/deployment/credentials.py
alertlogiccli/commands/deployment/installation.py
alertlogiccli/commands/deployment/mode.py
alertlogiccli/commands/deployment/resources.py
alertlogiccli/commands/deployment/scan_queue.py
alertlogic_cli-1.5.8.dist-info/LICENSE.md
alertlogic_cli-1.5.8.dist-info/METADATA
alertlogic_cli-1.5.8.dist-info/WHEEL
alertlogic_cli-1.5.8.dist-info/entry_points.txt
alertlogic_cli-1.5.8.dist-info/top_level.txt
alertlogic_cli-1.5.8.dist-info/RECORD
