Metadata-Version: 2.1
Name: alertlogic-cli
Version: 1.5.8
Summary: Command Line Client for Alertlogic Services.
Home-page: https://github.com/alertlogic/alertlogic-cli
Author: Alert Logic Inc.
Author-email: support@alertlogic.com
License: MIT
Keywords: cli,alertlogic
Platform: any
Requires-Python: >=2.7, <3
Requires-Dist: requests (>=2.18)
Provides-Extra: dev
Requires-Dist: pytest (>=3) ; extra == 'dev'
Requires-Dist: mock (>=2.0.0) ; extra == 'dev'
Requires-Dist: httpretty (>=0.8.14) ; extra == 'dev'
Requires-Dist: pycodestyle (>=2.3.1) ; extra == 'dev'
